brute_guard/__init__.py
brute_guard/settings.py
brute_guard/sqlite3/__init__.py
brute_guard/sqlite3/blocking.py
brute_guard/sqlite3/brute_guard.py
brute_guard/sqlite3/control.py
tests/__init__.py
tests/conftest.py
tests/test_sqlite3.py
brute_guard-0.1.0.dist-info/METADATA
brute_guard-0.1.0.dist-info/WHEEL
brute_guard-0.1.0.dist-info/top_level.txt
brute_guard-0.1.0.dist-info/RECORD
