Metadata-Version: 2.1
Name: brute-guard
Version: 0.1.0
Summary: A Lightweight tool for preventing Brute Force Attacks
Author: Igor Rodrigues Sousa Silva
License: MIT
Keywords: security brute force attack authentications auth cybersecurity
Classifier: Development Status :: 3 - Alpha
Classifier: Intended Audience :: Developers
Classifier: Topic :: Software Development :: Build Tools
Classifier: License :: OSI Approved :: MIT License
Classifier: Programming Language :: Python :: 3.7
Classifier: Programming Language :: Python :: 3.8
Classifier: Programming Language :: Python :: 3.9
Classifier: Programming Language :: Python :: 3.10
Requires-Python: >=3.7
